pygitscrum/__init__.py
pygitscrum/args.py
pygitscrum/git.py
pygitscrum/git_check.py
pygitscrum/git_daily.py
pygitscrum/git_fetch.py
pygitscrum/git_prune.py
pygitscrum/git_search.py
pygitscrum/git_show.py
pygitscrum/git_track.py
pygitscrum/git_wip.py
pygitscrum/print.py
pygitscrum/scan.py
pygitscrum/update.py
pygitscrum/version.py
pygitscrum-0.4.4.dist-info/LICENSE.txt
pygitscrum-0.4.4.dist-info/METADATA
pygitscrum-0.4.4.dist-info/WHEEL
pygitscrum-0.4.4.dist-info/entry_points.txt
pygitscrum-0.4.4.dist-info/top_level.txt
pygitscrum-0.4.4.dist-info/RECORD
