Metadata-Version: 2.1
Name: pygitscrum
Version: 0.4.4
Summary: pygitscrum
Home-page: https://github.com/thib1984/pygitscrum
Author: thib1984
Author-email: thibault.garcon@gmail.com
License: MIT
Platform: UNKNOWN
Classifier: Programming Language :: Python :: 3.6
Classifier: Programming Language :: Python :: 3.7
Classifier: Programming Language :: Python :: 3.8
Classifier: Programming Language :: Python :: 3.9
Classifier: Programming Language :: Python :: 3.10
Classifier: License :: OSI Approved :: MIT License
Classifier: Operating System :: OS Independent
Requires-Python: >=3.6
License-File: LICENSE.txt
Requires-Dist: termcolor
Requires-Dist: colorama
